<?xml version="1.0" encoding="ISO-8859-1"?>
<NetSim_Metrics>
 <!--NETSIM_METRICS-->
 <MENU Name="Link_Metrics">
  <TABLE name="Link_Metrics">
   <TH name="Link ID" isShow="true"/>
   <TH name="Link Throughput Plot" isShow="true"/>
   <TH name="Packets Transmitted" isShow="true">
    <TH name="Data"/>
    <TH name="Control"/>
   </TH>
   <TH name="Packets Errored" isShow="true">
    <TH name="Data"/>
    <TH name="Control"/>
   </TH>
   <TH name="Packets Collided" isShow="true">
    <TH name="Data"/>
    <TH name="Control"/>
   </TH>
   <TH name="Bytes Transmitted(bytes)" isShow="false"/>
   <TH name="Payload Transmitted(bytes)" isShow="false"/>
   <TH name="Overhead Transmitted(bytes)" isShow="false"/>
   <TR>
    <TC Value="All"/>
    <TC Value="NA"/>
    <TC Value="694672"/>
    <TC Value="0"/>
    <TC Value="0"/>
    <TC Value="0"/>
    <TC Value="216332"/>
    <TC Value="0"/>
    <TC Value="49321712"/>
    <TC Value="9566800"/>
    <TC Value="39754912"/>
   </TR>
   <TR>
    <TC Value="1"/>
    <TC Value="NA"/>
    <TC Value="694672"/>
    <TC Value="0"/>
    <TC Value="0"/>
    <TC Value="0"/>
    <TC Value="216332"/>
    <TC Value="0"/>
    <TC Value="49321712"/>
    <TC Value="9566800"/>
    <TC Value="39754912"/>
   </TR>
  </TABLE>
 </MENU>
 <MENU Name="Queue_Metrics">
  <TABLE name="Queue_Metrics">
   <TH name="Device_id" isShow="true"/>
   <TH name="Port_id" isShow="true"/>
   <TH name="Queued_packet" isShow="true"/>
   <TH name="Dequeued_packet" isShow="true"/>
   <TH name="Dropped_packet" isShow="true"/>
  </TABLE>
 </MENU>
 <MENU Name="TCP_Metrics">
  <TABLE name="TCP_Metrics">
   <TH name="Source" isShow="true"/>
   <TH name="Destination" isShow="true"/>
   <TH name="Local Address" isShow="false"/>
   <TH name="Remote Address" isShow="false"/>
   <TH name="Syn Sent" isShow="false"/>
   <TH name="Syn-Ack Sent" isShow="false"/>
   <TH name="Segment Sent" isShow="true"/>
   <TH name="Segment Received" isShow="true"/>
   <TH name="Segment Retransmitted" isShow="false"/>
   <TH name="Ack Sent" isShow="true"/>
   <TH name="Ack Received" isShow="true"/>
   <TH name="Duplicate segment received" isShow="false"/>
   <TH name="Out of order segment received" isShow="false"/>
   <TH name="Duplicate ack received" isShow="true"/>
   <TH name="Times RTO expired" isShow="false"/>
   <TR>
    <TC Value="T_0"/>
    <TC Value="ANY_DEVICE"/>
    <TC Value="11.1.1.1:0"/>
    <TC Value="0.0.0.0:0"/>
    <TC Value="0"/>
    <TC Value="0"/>
    <TC Value="0"/>
    <TC Value="0"/>
    <TC Value="0"/>
    <TC Value="0"/>
    <TC Value="0"/>
    <TC Value="0"/>
    <TC Value="0"/>
    <TC Value="0"/>
    <TC Value="0"/>
   </TR>
   <TR>
    <TC Value="T_1"/>
    <TC Value="ANY_DEVICE"/>
    <TC Value="11.1.1.2:0"/>
    <TC Value="0.0.0.0:0"/>
    <TC Value="0"/>
    <TC Value="0"/>
    <TC Value="0"/>
    <TC Value="0"/>
    <TC Value="0"/>
    <TC Value="0"/>
    <TC Value="0"/>
    <TC Value="0"/>
    <TC Value="0"/>
    <TC Value="0"/>
    <TC Value="0"/>
   </TR>
   <TR>
    <TC Value="T_2"/>
    <TC Value="ANY_DEVICE"/>
    <TC Value="11.1.1.3:0"/>
    <TC Value="0.0.0.0:0"/>
    <TC Value="0"/>
    <TC Value="0"/>
    <TC Value="0"/>
    <TC Value="0"/>
    <TC Value="0"/>
    <TC Value="0"/>
    <TC Value="0"/>
    <TC Value="0"/>
    <TC Value="0"/>
    <TC Value="0"/>
    <TC Value="0"/>
   </TR>
   <TR>
    <TC Value="T_3"/>
    <TC Value="ANY_DEVICE"/>
    <TC Value="11.1.1.4:0"/>
    <TC Value="0.0.0.0:0"/>
    <TC Value="0"/>
    <TC Value="0"/>
    <TC Value="0"/>
    <TC Value="0"/>
    <TC Value="0"/>
    <TC Value="0"/>
    <TC Value="0"/>
    <TC Value="0"/>
    <TC Value="0"/>
    <TC Value="0"/>
    <TC Value="0"/>
   </TR>
   <TR>
    <TC Value="T_4"/>
    <TC Value="ANY_DEVICE"/>
    <TC Value="11.1.1.5:0"/>
    <TC Value="0.0.0.0:0"/>
    <TC Value="0"/>
    <TC Value="0"/>
    <TC Value="0"/>
    <TC Value="0"/>
    <TC Value="0"/>
    <TC Value="0"/>
    <TC Value="0"/>
    <TC Value="0"/>
    <TC Value="0"/>
    <TC Value="0"/>
    <TC Value="0"/>
   </TR>
   <TR>
    <TC Value="T_5"/>
    <TC Value="ANY_DEVICE"/>
    <TC Value="11.1.1.6:0"/>
    <TC Value="0.0.0.0:0"/>
    <TC Value="0"/>
    <TC Value="0"/>
    <TC Value="0"/>
    <TC Value="0"/>
    <TC Value="0"/>
    <TC Value="0"/>
    <TC Value="0"/>
    <TC Value="0"/>
    <TC Value="0"/>
    <TC Value="0"/>
    <TC Value="0"/>
   </TR>
   <TR>
    <TC Value="T_6"/>
    <TC Value="ANY_DEVICE"/>
    <TC Value="11.1.1.7:0"/>
    <TC Value="0.0.0.0:0"/>
    <TC Value="0"/>
    <TC Value="0"/>
    <TC Value="0"/>
    <TC Value="0"/>
    <TC Value="0"/>
    <TC Value="0"/>
    <TC Value="0"/>
    <TC Value="0"/>
    <TC Value="0"/>
    <TC Value="0"/>
    <TC Value="0"/>
   </TR>
   <TR>
    <TC Value="T_7"/>
    <TC Value="ANY_DEVICE"/>
    <TC Value="11.1.1.8:0"/>
    <TC Value="0.0.0.0:0"/>
    <TC Value="0"/>
    <TC Value="0"/>
    <TC Value="0"/>
    <TC Value="0"/>
    <TC Value="0"/>
    <TC Value="0"/>
    <TC Value="0"/>
    <TC Value="0"/>
    <TC Value="0"/>
    <TC Value="0"/>
    <TC Value="0"/>
   </TR>
   <TR>
    <TC Value="T_8"/>
    <TC Value="ANY_DEVICE"/>
    <TC Value="11.1.1.9:0"/>
    <TC Value="0.0.0.0:0"/>
    <TC Value="0"/>
    <TC Value="0"/>
    <TC Value="0"/>
    <TC Value="0"/>
    <TC Value="0"/>
    <TC Value="0"/>
    <TC Value="0"/>
    <TC Value="0"/>
    <TC Value="0"/>
    <TC Value="0"/>
    <TC Value="0"/>
   </TR>
   <TR>
    <TC Value="T_9"/>
    <TC Value="ANY_DEVICE"/>
    <TC Value="11.1.1.10:0"/>
    <TC Value="0.0.0.0:0"/>
    <TC Value="0"/>
    <TC Value="0"/>
    <TC Value="0"/>
    <TC Value="0"/>
    <TC Value="0"/>
    <TC Value="0"/>
    <TC Value="0"/>
    <TC Value="0"/>
    <TC Value="0"/>
    <TC Value="0"/>
    <TC Value="0"/>
   </TR>
   <TR>
    <TC Value="RSU_11"/>
    <TC Value="ANY_DEVICE"/>
    <TC Value="11.1.1.11:0"/>
    <TC Value="0.0.0.0:0"/>
    <TC Value="0"/>
    <TC Value="0"/>
    <TC Value="0"/>
    <TC Value="0"/>
    <TC Value="0"/>
    <TC Value="0"/>
    <TC Value="0"/>
    <TC Value="0"/>
    <TC Value="0"/>
    <TC Value="0"/>
    <TC Value="0"/>
   </TR>
  </TABLE>
 </MENU>
 <MENU Name="IP_Metrics">
  <TABLE name="IP_Metrics">
   <TH name="Device Id" isShow="true"/>
   <TH name="Packet sent" isShow="true"/>
   <TH name="Packet forwarded" isShow="true"/>
   <TH name="Packet received" isShow="true"/>
   <TH name="Packet discarded" isShow="false"/>
   <TH name="TTL expired" isShow="false"/>
   <TH name="Firewall blocked" isShow="false"/>
   <TR>
    <TC Value="1"/>
    <TC Value="0"/>
    <TC Value="0"/>
    <TC Value="33475"/>
    <TC Value="0"/>
    <TC Value="0"/>
    <TC Value="0"/>
   </TR>
   <TR>
    <TC Value="2"/>
    <TC Value="0"/>
    <TC Value="0"/>
    <TC Value="52505"/>
    <TC Value="0"/>
    <TC Value="0"/>
    <TC Value="0"/>
   </TR>
   <TR>
    <TC Value="3"/>
    <TC Value="0"/>
    <TC Value="0"/>
    <TC Value="52139"/>
    <TC Value="0"/>
    <TC Value="0"/>
    <TC Value="0"/>
   </TR>
   <TR>
    <TC Value="4"/>
    <TC Value="0"/>
    <TC Value="0"/>
    <TC Value="50823"/>
    <TC Value="0"/>
    <TC Value="0"/>
    <TC Value="0"/>
   </TR>
   <TR>
    <TC Value="5"/>
    <TC Value="0"/>
    <TC Value="0"/>
    <TC Value="48579"/>
    <TC Value="0"/>
    <TC Value="0"/>
    <TC Value="0"/>
   </TR>
   <TR>
    <TC Value="6"/>
    <TC Value="0"/>
    <TC Value="0"/>
    <TC Value="45614"/>
    <TC Value="0"/>
    <TC Value="0"/>
    <TC Value="0"/>
   </TR>
   <TR>
    <TC Value="7"/>
    <TC Value="0"/>
    <TC Value="0"/>
    <TC Value="41304"/>
    <TC Value="0"/>
    <TC Value="0"/>
    <TC Value="0"/>
   </TR>
   <TR>
    <TC Value="8"/>
    <TC Value="0"/>
    <TC Value="0"/>
    <TC Value="38283"/>
    <TC Value="0"/>
    <TC Value="0"/>
    <TC Value="0"/>
   </TR>
   <TR>
    <TC Value="9"/>
    <TC Value="0"/>
    <TC Value="0"/>
    <TC Value="35833"/>
    <TC Value="0"/>
    <TC Value="0"/>
    <TC Value="0"/>
   </TR>
   <TR>
    <TC Value="10"/>
    <TC Value="0"/>
    <TC Value="0"/>
    <TC Value="34267"/>
    <TC Value="0"/>
    <TC Value="0"/>
    <TC Value="0"/>
   </TR>
   <TR>
    <TC Value="11"/>
    <TC Value="0"/>
    <TC Value="0"/>
    <TC Value="45518"/>
    <TC Value="0"/>
    <TC Value="0"/>
    <TC Value="0"/>
   </TR>
  </TABLE>
 </MENU>
 <MENU Name="IP_Forwarding_Table">
  <MENU Name="T_0">
   <TABLE name="T_0">
    <TH name="Network Destination" isShow="true"/>
    <TH name="Netmask/Prefix len" isShow="true"/>
    <TH name="Gateway" isShow="true"/>
    <TH name="Interface" isShow="true"/>
    <TH name="Metrics" isShow="false"/>
    <TH name="Type" isShow="false"/>
    <TR>
     <TC Value="11.1.0.0"/>
     <TC Value="255.255.0.0"/>
     <TC Value="on-link"/>
     <TC Value="11.1.1.1 "/>
     <TC Value="300"/>
     <TC Value="LOCAL"/>
    </TR>
    <TR>
     <TC Value="224.0.0.1"/>
     <TC Value="255.255.255.255"/>
     <TC Value="on-link"/>
     <TC Value="11.1.1.1 "/>
     <TC Value="306"/>
     <TC Value="MULTICAST"/>
    </TR>
    <TR>
     <TC Value="224.0.0.0"/>
     <TC Value="240.0.0.0"/>
     <TC Value="on-link"/>
     <TC Value="11.1.1.1 "/>
     <TC Value="306"/>
     <TC Value="MULTICAST"/>
    </TR>
    <TR>
     <TC Value="255.255.255.255"/>
     <TC Value="255.255.255.255"/>
     <TC Value="on-link"/>
     <TC Value="11.1.1.1 "/>
     <TC Value="999"/>
     <TC Value="BROADCAST"/>
    </TR>
   </TABLE>
  </MENU>
  <MENU Name="T_1">
   <TABLE name="T_1">
    <TH name="Network Destination" isShow="true"/>
    <TH name="Netmask/Prefix len" isShow="true"/>
    <TH name="Gateway" isShow="true"/>
    <TH name="Interface" isShow="true"/>
    <TH name="Metrics" isShow="false"/>
    <TH name="Type" isShow="false"/>
    <TR>
     <TC Value="11.1.0.0"/>
     <TC Value="255.255.0.0"/>
     <TC Value="on-link"/>
     <TC Value="11.1.1.2 "/>
     <TC Value="300"/>
     <TC Value="LOCAL"/>
    </TR>
    <TR>
     <TC Value="224.0.0.1"/>
     <TC Value="255.255.255.255"/>
     <TC Value="on-link"/>
     <TC Value="11.1.1.2 "/>
     <TC Value="306"/>
     <TC Value="MULTICAST"/>
    </TR>
    <TR>
     <TC Value="224.0.0.0"/>
     <TC Value="240.0.0.0"/>
     <TC Value="on-link"/>
     <TC Value="11.1.1.2 "/>
     <TC Value="306"/>
     <TC Value="MULTICAST"/>
    </TR>
    <TR>
     <TC Value="255.255.255.255"/>
     <TC Value="255.255.255.255"/>
     <TC Value="on-link"/>
     <TC Value="11.1.1.2 "/>
     <TC Value="999"/>
     <TC Value="BROADCAST"/>
    </TR>
   </TABLE>
  </MENU>
  <MENU Name="T_2">
   <TABLE name="T_2">
    <TH name="Network Destination" isShow="true"/>
    <TH name="Netmask/Prefix len" isShow="true"/>
    <TH name="Gateway" isShow="true"/>
    <TH name="Interface" isShow="true"/>
    <TH name="Metrics" isShow="false"/>
    <TH name="Type" isShow="false"/>
    <TR>
     <TC Value="11.1.0.0"/>
     <TC Value="255.255.0.0"/>
     <TC Value="on-link"/>
     <TC Value="11.1.1.3 "/>
     <TC Value="300"/>
     <TC Value="LOCAL"/>
    </TR>
    <TR>
     <TC Value="224.0.0.1"/>
     <TC Value="255.255.255.255"/>
     <TC Value="on-link"/>
     <TC Value="11.1.1.3 "/>
     <TC Value="306"/>
     <TC Value="MULTICAST"/>
    </TR>
    <TR>
     <TC Value="224.0.0.0"/>
     <TC Value="240.0.0.0"/>
     <TC Value="on-link"/>
     <TC Value="11.1.1.3 "/>
     <TC Value="306"/>
     <TC Value="MULTICAST"/>
    </TR>
    <TR>
     <TC Value="255.255.255.255"/>
     <TC Value="255.255.255.255"/>
     <TC Value="on-link"/>
     <TC Value="11.1.1.3 "/>
     <TC Value="999"/>
     <TC Value="BROADCAST"/>
    </TR>
   </TABLE>
  </MENU>
  <MENU Name="T_3">
   <TABLE name="T_3">
    <TH name="Network Destination" isShow="true"/>
    <TH name="Netmask/Prefix len" isShow="true"/>
    <TH name="Gateway" isShow="true"/>
    <TH name="Interface" isShow="true"/>
    <TH name="Metrics" isShow="false"/>
    <TH name="Type" isShow="false"/>
    <TR>
     <TC Value="11.1.0.0"/>
     <TC Value="255.255.0.0"/>
     <TC Value="on-link"/>
     <TC Value="11.1.1.4 "/>
     <TC Value="300"/>
     <TC Value="LOCAL"/>
    </TR>
    <TR>
     <TC Value="224.0.0.1"/>
     <TC Value="255.255.255.255"/>
     <TC Value="on-link"/>
     <TC Value="11.1.1.4 "/>
     <TC Value="306"/>
     <TC Value="MULTICAST"/>
    </TR>
    <TR>
     <TC Value="224.0.0.0"/>
     <TC Value="240.0.0.0"/>
     <TC Value="on-link"/>
     <TC Value="11.1.1.4 "/>
     <TC Value="306"/>
     <TC Value="MULTICAST"/>
    </TR>
    <TR>
     <TC Value="255.255.255.255"/>
     <TC Value="255.255.255.255"/>
     <TC Value="on-link"/>
     <TC Value="11.1.1.4 "/>
     <TC Value="999"/>
     <TC Value="BROADCAST"/>
    </TR>
   </TABLE>
  </MENU>
  <MENU Name="T_4">
   <TABLE name="T_4">
    <TH name="Network Destination" isShow="true"/>
    <TH name="Netmask/Prefix len" isShow="true"/>
    <TH name="Gateway" isShow="true"/>
    <TH name="Interface" isShow="true"/>
    <TH name="Metrics" isShow="false"/>
    <TH name="Type" isShow="false"/>
    <TR>
     <TC Value="11.1.0.0"/>
     <TC Value="255.255.0.0"/>
     <TC Value="on-link"/>
     <TC Value="11.1.1.5 "/>
     <TC Value="300"/>
     <TC Value="LOCAL"/>
    </TR>
    <TR>
     <TC Value="224.0.0.1"/>
     <TC Value="255.255.255.255"/>
     <TC Value="on-link"/>
     <TC Value="11.1.1.5 "/>
     <TC Value="306"/>
     <TC Value="MULTICAST"/>
    </TR>
    <TR>
     <TC Value="224.0.0.0"/>
     <TC Value="240.0.0.0"/>
     <TC Value="on-link"/>
     <TC Value="11.1.1.5 "/>
     <TC Value="306"/>
     <TC Value="MULTICAST"/>
    </TR>
    <TR>
     <TC Value="255.255.255.255"/>
     <TC Value="255.255.255.255"/>
     <TC Value="on-link"/>
     <TC Value="11.1.1.5 "/>
     <TC Value="999"/>
     <TC Value="BROADCAST"/>
    </TR>
   </TABLE>
  </MENU>
  <MENU Name="T_5">
   <TABLE name="T_5">
    <TH name="Network Destination" isShow="true"/>
    <TH name="Netmask/Prefix len" isShow="true"/>
    <TH name="Gateway" isShow="true"/>
    <TH name="Interface" isShow="true"/>
    <TH name="Metrics" isShow="false"/>
    <TH name="Type" isShow="false"/>
    <TR>
     <TC Value="11.1.0.0"/>
     <TC Value="255.255.0.0"/>
     <TC Value="on-link"/>
     <TC Value="11.1.1.6 "/>
     <TC Value="300"/>
     <TC Value="LOCAL"/>
    </TR>
    <TR>
     <TC Value="224.0.0.1"/>
     <TC Value="255.255.255.255"/>
     <TC Value="on-link"/>
     <TC Value="11.1.1.6 "/>
     <TC Value="306"/>
     <TC Value="MULTICAST"/>
    </TR>
    <TR>
     <TC Value="224.0.0.0"/>
     <TC Value="240.0.0.0"/>
     <TC Value="on-link"/>
     <TC Value="11.1.1.6 "/>
     <TC Value="306"/>
     <TC Value="MULTICAST"/>
    </TR>
    <TR>
     <TC Value="255.255.255.255"/>
     <TC Value="255.255.255.255"/>
     <TC Value="on-link"/>
     <TC Value="11.1.1.6 "/>
     <TC Value="999"/>
     <TC Value="BROADCAST"/>
    </TR>
   </TABLE>
  </MENU>
  <MENU Name="T_6">
   <TABLE name="T_6">
    <TH name="Network Destination" isShow="true"/>
    <TH name="Netmask/Prefix len" isShow="true"/>
    <TH name="Gateway" isShow="true"/>
    <TH name="Interface" isShow="true"/>
    <TH name="Metrics" isShow="false"/>
    <TH name="Type" isShow="false"/>
    <TR>
     <TC Value="11.1.0.0"/>
     <TC Value="255.255.0.0"/>
     <TC Value="on-link"/>
     <TC Value="11.1.1.7 "/>
     <TC Value="300"/>
     <TC Value="LOCAL"/>
    </TR>
    <TR>
     <TC Value="224.0.0.1"/>
     <TC Value="255.255.255.255"/>
     <TC Value="on-link"/>
     <TC Value="11.1.1.7 "/>
     <TC Value="306"/>
     <TC Value="MULTICAST"/>
    </TR>
    <TR>
     <TC Value="224.0.0.0"/>
     <TC Value="240.0.0.0"/>
     <TC Value="on-link"/>
     <TC Value="11.1.1.7 "/>
     <TC Value="306"/>
     <TC Value="MULTICAST"/>
    </TR>
    <TR>
     <TC Value="255.255.255.255"/>
     <TC Value="255.255.255.255"/>
     <TC Value="on-link"/>
     <TC Value="11.1.1.7 "/>
     <TC Value="999"/>
     <TC Value="BROADCAST"/>
    </TR>
   </TABLE>
  </MENU>
  <MENU Name="T_7">
   <TABLE name="T_7">
    <TH name="Network Destination" isShow="true"/>
    <TH name="Netmask/Prefix len" isShow="true"/>
    <TH name="Gateway" isShow="true"/>
    <TH name="Interface" isShow="true"/>
    <TH name="Metrics" isShow="false"/>
    <TH name="Type" isShow="false"/>
    <TR>
     <TC Value="11.1.0.0"/>
     <TC Value="255.255.0.0"/>
     <TC Value="on-link"/>
     <TC Value="11.1.1.8 "/>
     <TC Value="300"/>
     <TC Value="LOCAL"/>
    </TR>
    <TR>
     <TC Value="224.0.0.1"/>
     <TC Value="255.255.255.255"/>
     <TC Value="on-link"/>
     <TC Value="11.1.1.8 "/>
     <TC Value="306"/>
     <TC Value="MULTICAST"/>
    </TR>
    <TR>
     <TC Value="224.0.0.0"/>
     <TC Value="240.0.0.0"/>
     <TC Value="on-link"/>
     <TC Value="11.1.1.8 "/>
     <TC Value="306"/>
     <TC Value="MULTICAST"/>
    </TR>
    <TR>
     <TC Value="255.255.255.255"/>
     <TC Value="255.255.255.255"/>
     <TC Value="on-link"/>
     <TC Value="11.1.1.8 "/>
     <TC Value="999"/>
     <TC Value="BROADCAST"/>
    </TR>
   </TABLE>
  </MENU>
  <MENU Name="T_8">
   <TABLE name="T_8">
    <TH name="Network Destination" isShow="true"/>
    <TH name="Netmask/Prefix len" isShow="true"/>
    <TH name="Gateway" isShow="true"/>
    <TH name="Interface" isShow="true"/>
    <TH name="Metrics" isShow="false"/>
    <TH name="Type" isShow="false"/>
    <TR>
     <TC Value="11.1.0.0"/>
     <TC Value="255.255.0.0"/>
     <TC Value="on-link"/>
     <TC Value="11.1.1.9 "/>
     <TC Value="300"/>
     <TC Value="LOCAL"/>
    </TR>
    <TR>
     <TC Value="224.0.0.1"/>
     <TC Value="255.255.255.255"/>
     <TC Value="on-link"/>
     <TC Value="11.1.1.9 "/>
     <TC Value="306"/>
     <TC Value="MULTICAST"/>
    </TR>
    <TR>
     <TC Value="224.0.0.0"/>
     <TC Value="240.0.0.0"/>
     <TC Value="on-link"/>
     <TC Value="11.1.1.9 "/>
     <TC Value="306"/>
     <TC Value="MULTICAST"/>
    </TR>
    <TR>
     <TC Value="255.255.255.255"/>
     <TC Value="255.255.255.255"/>
     <TC Value="on-link"/>
     <TC Value="11.1.1.9 "/>
     <TC Value="999"/>
     <TC Value="BROADCAST"/>
    </TR>
   </TABLE>
  </MENU>
  <MENU Name="T_9">
   <TABLE name="T_9">
    <TH name="Network Destination" isShow="true"/>
    <TH name="Netmask/Prefix len" isShow="true"/>
    <TH name="Gateway" isShow="true"/>
    <TH name="Interface" isShow="true"/>
    <TH name="Metrics" isShow="false"/>
    <TH name="Type" isShow="false"/>
    <TR>
     <TC Value="11.1.0.0"/>
     <TC Value="255.255.0.0"/>
     <TC Value="on-link"/>
     <TC Value="11.1.1.10 "/>
     <TC Value="300"/>
     <TC Value="LOCAL"/>
    </TR>
    <TR>
     <TC Value="224.0.0.1"/>
     <TC Value="255.255.255.255"/>
     <TC Value="on-link"/>
     <TC Value="11.1.1.10 "/>
     <TC Value="306"/>
     <TC Value="MULTICAST"/>
    </TR>
    <TR>
     <TC Value="224.0.0.0"/>
     <TC Value="240.0.0.0"/>
     <TC Value="on-link"/>
     <TC Value="11.1.1.10 "/>
     <TC Value="306"/>
     <TC Value="MULTICAST"/>
    </TR>
    <TR>
     <TC Value="255.255.255.255"/>
     <TC Value="255.255.255.255"/>
     <TC Value="on-link"/>
     <TC Value="11.1.1.10 "/>
     <TC Value="999"/>
     <TC Value="BROADCAST"/>
    </TR>
   </TABLE>
  </MENU>
  <MENU Name="RSU_11">
   <TABLE name="RSU_11">
    <TH name="Network Destination" isShow="true"/>
    <TH name="Netmask/Prefix len" isShow="true"/>
    <TH name="Gateway" isShow="true"/>
    <TH name="Interface" isShow="true"/>
    <TH name="Metrics" isShow="false"/>
    <TH name="Type" isShow="false"/>
    <TR>
     <TC Value="11.1.0.0"/>
     <TC Value="255.255.0.0"/>
     <TC Value="on-link"/>
     <TC Value="11.1.1.11 "/>
     <TC Value="300"/>
     <TC Value="LOCAL"/>
    </TR>
    <TR>
     <TC Value="224.0.0.1"/>
     <TC Value="255.255.255.255"/>
     <TC Value="on-link"/>
     <TC Value="11.1.1.11 "/>
     <TC Value="306"/>
     <TC Value="MULTICAST"/>
    </TR>
    <TR>
     <TC Value="224.0.0.0"/>
     <TC Value="240.0.0.0"/>
     <TC Value="on-link"/>
     <TC Value="11.1.1.11 "/>
     <TC Value="306"/>
     <TC Value="MULTICAST"/>
    </TR>
    <TR>
     <TC Value="255.255.255.255"/>
     <TC Value="255.255.255.255"/>
     <TC Value="on-link"/>
     <TC Value="11.1.1.11 "/>
     <TC Value="999"/>
     <TC Value="BROADCAST"/>
    </TR>
   </TABLE>
  </MENU>
 </MENU>
 <MENU Name="DSR Metrics">
  <TABLE name="DSR Metrics">
   <TH name="Device Id" isShow="true"/>
   <TH name="RREQ Sent" isShow="true"/>
   <TH name="RREP Sent" isShow="false"/>
   <TH name="RERR Sent" isShow="false"/>
   <TH name="RREQ Forwarded" isShow="false"/>
   <TH name="RREP Forwarded" isShow="false"/>
   <TH name="RERR Forwarded" isShow="false"/>
   <TH name="Route Break" isShow="true"/>
   <TH name="Packet Originated" isShow="true"/>
   <TH name="Packet Transmitted" isShow="false"/>
   <TH name="Packet Received" isShow="true"/>
   <TH name="Packet Dropped" isShow="false"/>
   <TR>
    <TC Value="1"/>
    <TC Value="0"/>
    <TC Value="0"/>
    <TC Value="0"/>
    <TC Value="0"/>
    <TC Value="0"/>
    <TC Value="0"/>
    <TC Value="0"/>
    <TC Value="0"/>
    <TC Value="0"/>
    <TC Value="0"/>
    <TC Value="0"/>
   </TR>
   <TR>
    <TC Value="2"/>
    <TC Value="0"/>
    <TC Value="0"/>
    <TC Value="0"/>
    <TC Value="0"/>
    <TC Value="0"/>
    <TC Value="0"/>
    <TC Value="0"/>
    <TC Value="0"/>
    <TC Value="0"/>
    <TC Value="0"/>
    <TC Value="0"/>
   </TR>
   <TR>
    <TC Value="3"/>
    <TC Value="0"/>
    <TC Value="0"/>
    <TC Value="0"/>
    <TC Value="0"/>
    <TC Value="0"/>
    <TC Value="0"/>
    <TC Value="0"/>
    <TC Value="0"/>
    <TC Value="0"/>
    <TC Value="0"/>
    <TC Value="0"/>
   </TR>
   <TR>
    <TC Value="4"/>
    <TC Value="0"/>
    <TC Value="0"/>
    <TC Value="0"/>
    <TC Value="0"/>
    <TC Value="0"/>
    <TC Value="0"/>
    <TC Value="0"/>
    <TC Value="0"/>
    <TC Value="0"/>
    <TC Value="0"/>
    <TC Value="0"/>
   </TR>
   <TR>
    <TC Value="5"/>
    <TC Value="0"/>
    <TC Value="0"/>
    <TC Value="0"/>
    <TC Value="0"/>
    <TC Value="0"/>
    <TC Value="0"/>
    <TC Value="0"/>
    <TC Value="0"/>
    <TC Value="0"/>
    <TC Value="0"/>
    <TC Value="0"/>
   </TR>
   <TR>
    <TC Value="6"/>
    <TC Value="0"/>
    <TC Value="0"/>
    <TC Value="0"/>
    <TC Value="0"/>
    <TC Value="0"/>
    <TC Value="0"/>
    <TC Value="0"/>
    <TC Value="0"/>
    <TC Value="0"/>
    <TC Value="0"/>
    <TC Value="0"/>
   </TR>
   <TR>
    <TC Value="7"/>
    <TC Value="0"/>
    <TC Value="0"/>
    <TC Value="0"/>
    <TC Value="0"/>
    <TC Value="0"/>
    <TC Value="0"/>
    <TC Value="0"/>
    <TC Value="0"/>
    <TC Value="0"/>
    <TC Value="0"/>
    <TC Value="0"/>
   </TR>
   <TR>
    <TC Value="8"/>
    <TC Value="0"/>
    <TC Value="0"/>
    <TC Value="0"/>
    <TC Value="0"/>
    <TC Value="0"/>
    <TC Value="0"/>
    <TC Value="0"/>
    <TC Value="0"/>
    <TC Value="0"/>
    <TC Value="0"/>
    <TC Value="0"/>
   </TR>
   <TR>
    <TC Value="9"/>
    <TC Value="0"/>
    <TC Value="0"/>
    <TC Value="0"/>
    <TC Value="0"/>
    <TC Value="0"/>
    <TC Value="0"/>
    <TC Value="0"/>
    <TC Value="0"/>
    <TC Value="0"/>
    <TC Value="0"/>
    <TC Value="0"/>
   </TR>
   <TR>
    <TC Value="10"/>
    <TC Value="0"/>
    <TC Value="0"/>
    <TC Value="0"/>
    <TC Value="0"/>
    <TC Value="0"/>
    <TC Value="0"/>
    <TC Value="0"/>
    <TC Value="0"/>
    <TC Value="0"/>
    <TC Value="0"/>
    <TC Value="0"/>
   </TR>
   <TR>
    <TC Value="11"/>
    <TC Value="0"/>
    <TC Value="0"/>
    <TC Value="0"/>
    <TC Value="0"/>
    <TC Value="0"/>
    <TC Value="0"/>
    <TC Value="0"/>
    <TC Value="0"/>
    <TC Value="0"/>
    <TC Value="0"/>
    <TC Value="0"/>
   </TR>
  </TABLE>
 </MENU>
 <MENU Name="IEEE802.11_Metrics">
  <TABLE name="IEEE802.11_Metrics">
   <TH name="DeviceId" isShow="true"/>
   <TH name="InterfaceId" isShow="true"/>
   <TH name="Frame Sent" isShow="true"/>
   <TH name="Frame Received" isShow="false"/>
   <TH name="RTS Sent" isShow="false"/>
   <TH name="RTS Received" isShow="false"/>
   <TH name="CTS Sent" isShow="false"/>
   <TH name="CTS Received" isShow="false"/>
   <TH name="Successful Backoff" isShow="false"/>
   <TH name="Failed Backoff" isShow="false"/>
   <TR>
    <TC Value="1"/>
    <TC Value="1"/>
    <TC Value="7211"/>
    <TC Value="33475"/>
    <TC Value="0"/>
    <TC Value="0"/>
    <TC Value="0"/>
    <TC Value="0"/>
    <TC Value="7211"/>
    <TC Value="31875"/>
   </TR>
   <TR>
    <TC Value="2"/>
    <TC Value="1"/>
    <TC Value="7253"/>
    <TC Value="52505"/>
    <TC Value="0"/>
    <TC Value="0"/>
    <TC Value="0"/>
    <TC Value="0"/>
    <TC Value="7253"/>
    <TC Value="1780"/>
   </TR>
   <TR>
    <TC Value="3"/>
    <TC Value="1"/>
    <TC Value="7244"/>
    <TC Value="52139"/>
    <TC Value="0"/>
    <TC Value="0"/>
    <TC Value="0"/>
    <TC Value="0"/>
    <TC Value="7244"/>
    <TC Value="0"/>
   </TR>
   <TR>
    <TC Value="4"/>
    <TC Value="1"/>
    <TC Value="7153"/>
    <TC Value="50823"/>
    <TC Value="0"/>
    <TC Value="0"/>
    <TC Value="0"/>
    <TC Value="0"/>
    <TC Value="7153"/>
    <TC Value="0"/>
   </TR>
   <TR>
    <TC Value="5"/>
    <TC Value="1"/>
    <TC Value="7158"/>
    <TC Value="48579"/>
    <TC Value="0"/>
    <TC Value="0"/>
    <TC Value="0"/>
    <TC Value="0"/>
    <TC Value="7158"/>
    <TC Value="0"/>
   </TR>
   <TR>
    <TC Value="6"/>
    <TC Value="1"/>
    <TC Value="7183"/>
    <TC Value="45614"/>
    <TC Value="0"/>
    <TC Value="0"/>
    <TC Value="0"/>
    <TC Value="0"/>
    <TC Value="7183"/>
    <TC Value="0"/>
   </TR>
   <TR>
    <TC Value="7"/>
    <TC Value="1"/>
    <TC Value="7121"/>
    <TC Value="41304"/>
    <TC Value="0"/>
    <TC Value="0"/>
    <TC Value="0"/>
    <TC Value="0"/>
    <TC Value="7121"/>
    <TC Value="0"/>
   </TR>
   <TR>
    <TC Value="8"/>
    <TC Value="1"/>
    <TC Value="7202"/>
    <TC Value="38283"/>
    <TC Value="0"/>
    <TC Value="0"/>
    <TC Value="0"/>
    <TC Value="0"/>
    <TC Value="7202"/>
    <TC Value="0"/>
   </TR>
   <TR>
    <TC Value="9"/>
    <TC Value="1"/>
    <TC Value="7088"/>
    <TC Value="35833"/>
    <TC Value="0"/>
    <TC Value="0"/>
    <TC Value="0"/>
    <TC Value="0"/>
    <TC Value="7088"/>
    <TC Value="0"/>
   </TR>
   <TR>
    <TC Value="10"/>
    <TC Value="1"/>
    <TC Value="7205"/>
    <TC Value="34267"/>
    <TC Value="0"/>
    <TC Value="0"/>
    <TC Value="0"/>
    <TC Value="0"/>
    <TC Value="7205"/>
    <TC Value="0"/>
   </TR>
   <TR>
    <TC Value="11"/>
    <TC Value="1"/>
    <TC Value="0"/>
    <TC Value="45518"/>
    <TC Value="0"/>
    <TC Value="0"/>
    <TC Value="0"/>
    <TC Value="0"/>
    <TC Value="0"/>
    <TC Value="0"/>
   </TR>
  </TABLE>
 </MENU>
 <MENU Name="Battery model">
  <TABLE name="Battery model">
   <TH name="Device Name" isShow="true"/>
   <TH name="Initial energy(mJ)" isShow="true"/>
   <TH name="Consumed energy(mJ)" isShow="true"/>
   <TH name="Remaining Energy(mJ)" isShow="true"/>
   <TH name="Transmitting energy(mJ)" isShow="false"/>
   <TH name="Receiving energy(mJ)" isShow="false"/>
   <TH name="Idle energy(mJ)" isShow="false"/>
   <TH name="Sleep energy(mJ)" isShow="false"/>
   <TR>
    <TC Value="T_0"/>
    <TC Value="6480.000000"/>
    <TC Value="910.536459"/>
    <TC Value="5655.776398"/>
    <TC Value="51.480654"/>
    <TC Value="253.379016"/>
    <TC Value="605.676788"/>
    <TC Value="0.000000"/>
   </TR>
   <TR>
    <TC Value="T_1"/>
    <TC Value="6480.000000"/>
    <TC Value="910.496050"/>
    <TC Value="5655.816807"/>
    <TC Value="51.925144"/>
    <TC Value="252.894118"/>
    <TC Value="605.676788"/>
    <TC Value="0.000000"/>
   </TR>
   <TR>
    <TC Value="T_2"/>
    <TC Value="6480.000000"/>
    <TC Value="910.509961"/>
    <TC Value="5655.802896"/>
    <TC Value="51.772123"/>
    <TC Value="253.061050"/>
    <TC Value="605.676788"/>
    <TC Value="0.000000"/>
   </TR>
   <TR>
    <TC Value="T_3"/>
    <TC Value="6480.000000"/>
    <TC Value="910.565606"/>
    <TC Value="5655.747252"/>
    <TC Value="51.160039"/>
    <TC Value="253.728778"/>
    <TC Value="605.676788"/>
    <TC Value="0.000000"/>
   </TR>
   <TR>
    <TC Value="T_4"/>
    <TC Value="6480.000000"/>
    <TC Value="910.570905"/>
    <TC Value="5655.741952"/>
    <TC Value="51.101745"/>
    <TC Value="253.792372"/>
    <TC Value="605.676788"/>
    <TC Value="0.000000"/>
   </TR>
   <TR>
    <TC Value="T_5"/>
    <TC Value="6480.000000"/>
    <TC Value="910.547720"/>
    <TC Value="5655.765137"/>
    <TC Value="51.356780"/>
    <TC Value="253.514151"/>
    <TC Value="605.676788"/>
    <TC Value="0.000000"/>
   </TR>
   <TR>
    <TC Value="T_6"/>
    <TC Value="6480.000000"/>
    <TC Value="910.584154"/>
    <TC Value="5655.728704"/>
    <TC Value="50.956011"/>
    <TC Value="253.951354"/>
    <TC Value="605.676788"/>
    <TC Value="0.000000"/>
   </TR>
   <TR>
    <TC Value="T_7"/>
    <TC Value="6480.000000"/>
    <TC Value="910.536459"/>
    <TC Value="5655.776398"/>
    <TC Value="51.480654"/>
    <TC Value="253.379016"/>
    <TC Value="605.676788"/>
    <TC Value="0.000000"/>
   </TR>
   <TR>
    <TC Value="T_8"/>
    <TC Value="6480.000000"/>
    <TC Value="910.613300"/>
    <TC Value="5655.699557"/>
    <TC Value="50.635395"/>
    <TC Value="254.301117"/>
    <TC Value="605.676788"/>
    <TC Value="0.000000"/>
   </TR>
   <TR>
    <TC Value="T_9"/>
    <TC Value="6480.000000"/>
    <TC Value="910.535796"/>
    <TC Value="5655.777061"/>
    <TC Value="51.487941"/>
    <TC Value="253.371067"/>
    <TC Value="605.676788"/>
    <TC Value="0.000000"/>
   </TR>
   <TR>
    <TC Value="RSU_11"/>
    <TC Value="6480.000000"/>
    <TC Value="915.216518"/>
    <TC Value="5651.096339"/>
    <TC Value="0.000000"/>
    <TC Value="309.539730"/>
    <TC Value="605.676788"/>
    <TC Value="0.000000"/>
   </TR>
  </TABLE>
 </MENU>
 <MENU Name="Application_Metrics">
  <TABLE name="Application_Metrics">
   <TH name="Application ID" isShow="true"/>
   <TH name="Application Name" isShow="true"/>
   <TH name="Source ID" isShow="false"/>
   <TH name="Destination ID" isShow="false"/>
   <TH name="Packets Generated" isShow="true"/>
   <TH name="Packets Received" isShow="true"/>
   <TH name="Payload generated (bytes)" isShow="false"/>
   <TH name="Payload received (bytes)" isShow="false"/>
   <TH name="Throughput (Mbps)" isShow="true"/>
   <TH name="Delay (microsec)" isShow="true"/>
   <TH name="Jitter (microsec)" isShow="true"/>
   <TR>
    <TC Value="1 (Aggregated)"/>
    <TC Value="App1_BSM"/>
    <TC Value="1"/>
    <TC Value="0"/>
    <TC Value="187499"/>
    <TC Value="30224"/>
    <TC Value="3749980"/>
    <TC Value="604480"/>
    <TC Value="0.080597"/>
    <TC Value="29885090.682804"/>
    <TC Value="0.000000"/>
   </TR>
   <TR>
    <TC Value="1"/>
    <TC Value="App1_BSM"/>
    <TC Value="1"/>
    <TC Value="2"/>
    <TC Value="187499"/>
    <TC Value="5833"/>
    <TC Value="3749980"/>
    <TC Value="116660"/>
    <TC Value="0.015555"/>
    <TC Value="28399987.600010"/>
    <TC Value="9885.321559"/>
   </TR>
   <TR>
    <TC Value="1"/>
    <TC Value="App1_BSM"/>
    <TC Value="1"/>
    <TC Value="3"/>
    <TC Value="187499"/>
    <TC Value="4461"/>
    <TC Value="3749980"/>
    <TC Value="89220"/>
    <TC Value="0.011896"/>
    <TC Value="28740001.825214"/>
    <TC Value="12924.121930"/>
   </TR>
   <TR>
    <TC Value="1"/>
    <TC Value="App1_BSM"/>
    <TC Value="1"/>
    <TC Value="4"/>
    <TC Value="187499"/>
    <TC Value="3414"/>
    <TC Value="3749980"/>
    <TC Value="68280"/>
    <TC Value="0.009104"/>
    <TC Value="29085484.559701"/>
    <TC Value="16887.029291"/>
   </TR>
   <TR>
    <TC Value="1"/>
    <TC Value="App1_BSM"/>
    <TC Value="1"/>
    <TC Value="5"/>
    <TC Value="187499"/>
    <TC Value="2742"/>
    <TC Value="3749980"/>
    <TC Value="54840"/>
    <TC Value="0.007312"/>
    <TC Value="29417417.871025"/>
    <TC Value="21026.229570"/>
   </TR>
   <TR>
    <TC Value="1"/>
    <TC Value="App1_BSM"/>
    <TC Value="1"/>
    <TC Value="6"/>
    <TC Value="187499"/>
    <TC Value="2281"/>
    <TC Value="3749980"/>
    <TC Value="45620"/>
    <TC Value="0.006083"/>
    <TC Value="29105716.975638"/>
    <TC Value="25276.620469"/>
   </TR>
   <TR>
    <TC Value="1"/>
    <TC Value="App1_BSM"/>
    <TC Value="1"/>
    <TC Value="7"/>
    <TC Value="187499"/>
    <TC Value="2173"/>
    <TC Value="3749980"/>
    <TC Value="43460"/>
    <TC Value="0.005795"/>
    <TC Value="29293549.445274"/>
    <TC Value="26533.319001"/>
   </TR>
   <TR>
    <TC Value="1"/>
    <TC Value="App1_BSM"/>
    <TC Value="1"/>
    <TC Value="8"/>
    <TC Value="187499"/>
    <TC Value="2203"/>
    <TC Value="3749980"/>
    <TC Value="44060"/>
    <TC Value="0.005875"/>
    <TC Value="29292485.790182"/>
    <TC Value="26171.829641"/>
   </TR>
   <TR>
    <TC Value="1"/>
    <TC Value="App1_BSM"/>
    <TC Value="1"/>
    <TC Value="9"/>
    <TC Value="187499"/>
    <TC Value="2223"/>
    <TC Value="3749980"/>
    <TC Value="44460"/>
    <TC Value="0.005928"/>
    <TC Value="29206742.820373"/>
    <TC Value="25936.293623"/>
   </TR>
   <TR>
    <TC Value="1"/>
    <TC Value="App1_BSM"/>
    <TC Value="1"/>
    <TC Value="10"/>
    <TC Value="187499"/>
    <TC Value="2306"/>
    <TC Value="3749980"/>
    <TC Value="46120"/>
    <TC Value="0.006149"/>
    <TC Value="29059502.739532"/>
    <TC Value="25002.568915"/>
   </TR>
   <TR>
    <TC Value="1"/>
    <TC Value="App1_BSM"/>
    <TC Value="1"/>
    <TC Value="11"/>
    <TC Value="187499"/>
    <TC Value="2588"/>
    <TC Value="3749980"/>
    <TC Value="51760"/>
    <TC Value="0.006901"/>
    <TC Value="39762800.898733"/>
    <TC Value="16021.895458"/>
   </TR>
   <TR>
    <TC Value="2 (Aggregated)"/>
    <TC Value="App2_BSM"/>
    <TC Value="2"/>
    <TC Value="0"/>
    <TC Value="187499"/>
    <TC Value="36546"/>
    <TC Value="3749980"/>
    <TC Value="730920"/>
    <TC Value="0.097456"/>
    <TC Value="29713370.549626"/>
    <TC Value="0.000000"/>
   </TR>
   <TR>
    <TC Value="2"/>
    <TC Value="App2_BSM"/>
    <TC Value="2"/>
    <TC Value="1"/>
    <TC Value="187499"/>
    <TC Value="6046"/>
    <TC Value="3749980"/>
    <TC Value="120920"/>
    <TC Value="0.016123"/>
    <TC Value="28693396.022688"/>
    <TC Value="9536.279763"/>
   </TR>
   <TR>
    <TC Value="2"/>
    <TC Value="App2_BSM"/>
    <TC Value="2"/>
    <TC Value="3"/>
    <TC Value="187499"/>
    <TC Value="6174"/>
    <TC Value="3749980"/>
    <TC Value="123480"/>
    <TC Value="0.016464"/>
    <TC Value="28879056.596131"/>
    <TC Value="9338.519943"/>
   </TR>
   <TR>
    <TC Value="2"/>
    <TC Value="App2_BSM"/>
    <TC Value="2"/>
    <TC Value="4"/>
    <TC Value="187499"/>
    <TC Value="4579"/>
    <TC Value="3749980"/>
    <TC Value="91580"/>
    <TC Value="0.012211"/>
    <TC Value="28825790.367371"/>
    <TC Value="12589.217630"/>
   </TR>
   <TR>
    <TC Value="2"/>
    <TC Value="App2_BSM"/>
    <TC Value="2"/>
    <TC Value="5"/>
    <TC Value="187499"/>
    <TC Value="3594"/>
    <TC Value="3749980"/>
    <TC Value="71880"/>
    <TC Value="0.009584"/>
    <TC Value="29482749.325612"/>
    <TC Value="16038.895244"/>
   </TR>
   <TR>
    <TC Value="2"/>
    <TC Value="App2_BSM"/>
    <TC Value="2"/>
    <TC Value="6"/>
    <TC Value="187499"/>
    <TC Value="2898"/>
    <TC Value="3749980"/>
    <TC Value="57960"/>
    <TC Value="0.007728"/>
    <TC Value="29011194.827609"/>
    <TC Value="19890.640411"/>
   </TR>
   <TR>
    <TC Value="2"/>
    <TC Value="App2_BSM"/>
    <TC Value="2"/>
    <TC Value="7"/>
    <TC Value="187499"/>
    <TC Value="2516"/>
    <TC Value="3749980"/>
    <TC Value="50320"/>
    <TC Value="0.006709"/>
    <TC Value="28788620.614173"/>
    <TC Value="22907.976457"/>
   </TR>
   <TR>
    <TC Value="2"/>
    <TC Value="App2_BSM"/>
    <TC Value="2"/>
    <TC Value="8"/>
    <TC Value="187499"/>
    <TC Value="2543"/>
    <TC Value="3749980"/>
    <TC Value="50860"/>
    <TC Value="0.006781"/>
    <TC Value="28858232.272131"/>
    <TC Value="22664.598611"/>
   </TR>
   <TR>
    <TC Value="2"/>
    <TC Value="App2_BSM"/>
    <TC Value="2"/>
    <TC Value="9"/>
    <TC Value="187499"/>
    <TC Value="2555"/>
    <TC Value="3749980"/>
    <TC Value="51100"/>
    <TC Value="0.006813"/>
    <TC Value="28808582.008963"/>
    <TC Value="22558.153097"/>
   </TR>
   <TR>
    <TC Value="2"/>
    <TC Value="App2_BSM"/>
    <TC Value="2"/>
    <TC Value="10"/>
    <TC Value="187499"/>
    <TC Value="2629"/>
    <TC Value="3749980"/>
    <TC Value="52580"/>
    <TC Value="0.007011"/>
    <TC Value="28757642.520411"/>
    <TC Value="21923.081488"/>
   </TR>
   <TR>
    <TC Value="2"/>
    <TC Value="App2_BSM"/>
    <TC Value="2"/>
    <TC Value="11"/>
    <TC Value="187499"/>
    <TC Value="3012"/>
    <TC Value="3749980"/>
    <TC Value="60240"/>
    <TC Value="0.008032"/>
    <TC Value="38867234.793416"/>
    <TC Value="14405.491010"/>
   </TR>
   <TR>
    <TC Value="3 (Aggregated)"/>
    <TC Value="App3_BSM"/>
    <TC Value="3"/>
    <TC Value="0"/>
    <TC Value="187499"/>
    <TC Value="41044"/>
    <TC Value="3749980"/>
    <TC Value="820880"/>
    <TC Value="0.109451"/>
    <TC Value="29355010.695889"/>
    <TC Value="0.000000"/>
   </TR>
   <TR>
    <TC Value="3"/>
    <TC Value="App3_BSM"/>
    <TC Value="3"/>
    <TC Value="1"/>
    <TC Value="187499"/>
    <TC Value="5298"/>
    <TC Value="3749980"/>
    <TC Value="105960"/>
    <TC Value="0.014128"/>
    <TC Value="28840377.655179"/>
    <TC Value="10881.647776"/>
   </TR>
   <TR>
    <TC Value="3"/>
    <TC Value="App3_BSM"/>
    <TC Value="3"/>
    <TC Value="2"/>
    <TC Value="187499"/>
    <TC Value="6480"/>
    <TC Value="3749980"/>
    <TC Value="129600"/>
    <TC Value="0.017280"/>
    <TC Value="28664270.858849"/>
    <TC Value="8897.815189"/>
   </TR>
   <TR>
    <TC Value="3"/>
    <TC Value="App3_BSM"/>
    <TC Value="3"/>
    <TC Value="4"/>
    <TC Value="187499"/>
    <TC Value="6102"/>
    <TC Value="3749980"/>
    <TC Value="122040"/>
    <TC Value="0.016272"/>
    <TC Value="28678174.716880"/>
    <TC Value="9448.582523"/>
   </TR>
   <TR>
    <TC Value="3"/>
    <TC Value="App3_BSM"/>
    <TC Value="3"/>
    <TC Value="5"/>
    <TC Value="187499"/>
    <TC Value="4591"/>
    <TC Value="3749980"/>
    <TC Value="91820"/>
    <TC Value="0.012243"/>
    <TC Value="28455359.560756"/>
    <TC Value="12555.908895"/>
   </TR>
   <TR>
    <TC Value="3"/>
    <TC Value="App3_BSM"/>
    <TC Value="3"/>
    <TC Value="6"/>
    <TC Value="187499"/>
    <TC Value="3673"/>
    <TC Value="3749980"/>
    <TC Value="73460"/>
    <TC Value="0.009795"/>
    <TC Value="29110138.871190"/>
    <TC Value="15693.372584"/>
   </TR>
   <TR>
    <TC Value="3"/>
    <TC Value="App3_BSM"/>
    <TC Value="3"/>
    <TC Value="7"/>
    <TC Value="187499"/>
    <TC Value="2832"/>
    <TC Value="3749980"/>
    <TC Value="56640"/>
    <TC Value="0.007552"/>
    <TC Value="28106991.716593"/>
    <TC Value="20353.778739"/>
   </TR>
   <TR>
    <TC Value="3"/>
    <TC Value="App3_BSM"/>
    <TC Value="3"/>
    <TC Value="8"/>
    <TC Value="187499"/>
    <TC Value="2887"/>
    <TC Value="3749980"/>
    <TC Value="57740"/>
    <TC Value="0.007699"/>
    <TC Value="28575932.155234"/>
    <TC Value="19966.057238"/>
   </TR>
   <TR>
    <TC Value="3"/>
    <TC Value="App3_BSM"/>
    <TC Value="3"/>
    <TC Value="9"/>
    <TC Value="187499"/>
    <TC Value="2919"/>
    <TC Value="3749980"/>
    <TC Value="58380"/>
    <TC Value="0.007784"/>
    <TC Value="28566925.659044"/>
    <TC Value="19747.140003"/>
   </TR>
   <TR>
    <TC Value="3"/>
    <TC Value="App3_BSM"/>
    <TC Value="3"/>
    <TC Value="10"/>
    <TC Value="187499"/>
    <TC Value="2932"/>
    <TC Value="3749980"/>
    <TC Value="58640"/>
    <TC Value="0.007819"/>
    <TC Value="28559633.506610"/>
    <TC Value="19659.567489"/>
   </TR>
   <TR>
    <TC Value="3"/>
    <TC Value="App3_BSM"/>
    <TC Value="3"/>
    <TC Value="11"/>
    <TC Value="187499"/>
    <TC Value="3330"/>
    <TC Value="3749980"/>
    <TC Value="66600"/>
    <TC Value="0.008880"/>
    <TC Value="37396554.644505"/>
    <TC Value="13609.891859"/>
   </TR>
   <TR>
    <TC Value="4 (Aggregated)"/>
    <TC Value="App4_BSM"/>
    <TC Value="4"/>
    <TC Value="0"/>
    <TC Value="187499"/>
    <TC Value="43040"/>
    <TC Value="3749980"/>
    <TC Value="860800"/>
    <TC Value="0.114773"/>
    <TC Value="29364432.437896"/>
    <TC Value="0.000000"/>
   </TR>
   <TR>
    <TC Value="4"/>
    <TC Value="App4_BSM"/>
    <TC Value="4"/>
    <TC Value="1"/>
    <TC Value="187499"/>
    <TC Value="4331"/>
    <TC Value="3749980"/>
    <TC Value="86620"/>
    <TC Value="0.011549"/>
    <TC Value="28893941.168545"/>
    <TC Value="13317.099402"/>
   </TR>
   <TR>
    <TC Value="4"/>
    <TC Value="App4_BSM"/>
    <TC Value="4"/>
    <TC Value="2"/>
    <TC Value="187499"/>
    <TC Value="5357"/>
    <TC Value="3749980"/>
    <TC Value="107140"/>
    <TC Value="0.014285"/>
    <TC Value="28747952.199184"/>
    <TC Value="10767.027481"/>
   </TR>
   <TR>
    <TC Value="4"/>
    <TC Value="App4_BSM"/>
    <TC Value="4"/>
    <TC Value="3"/>
    <TC Value="187499"/>
    <TC Value="6363"/>
    <TC Value="3749980"/>
    <TC Value="127260"/>
    <TC Value="0.016968"/>
    <TC Value="28791763.074583"/>
    <TC Value="9065.942400"/>
   </TR>
   <TR>
    <TC Value="4"/>
    <TC Value="App4_BSM"/>
    <TC Value="4"/>
    <TC Value="5"/>
    <TC Value="187499"/>
    <TC Value="6022"/>
    <TC Value="3749980"/>
    <TC Value="120440"/>
    <TC Value="0.016059"/>
    <TC Value="28723309.202506"/>
    <TC Value="9578.972239"/>
   </TR>
   <TR>
    <TC Value="4"/>
    <TC Value="App4_BSM"/>
    <TC Value="4"/>
    <TC Value="6"/>
    <TC Value="187499"/>
    <TC Value="4632"/>
    <TC Value="3749980"/>
    <TC Value="92640"/>
    <TC Value="0.012352"/>
    <TC Value="29005544.073949"/>
    <TC Value="12451.899151"/>
   </TR>
   <TR>
    <TC Value="4"/>
    <TC Value="App4_BSM"/>
    <TC Value="4"/>
    <TC Value="7"/>
    <TC Value="187499"/>
    <TC Value="3381"/>
    <TC Value="3749980"/>
    <TC Value="67620"/>
    <TC Value="0.009016"/>
    <TC Value="28143859.528589"/>
    <TC Value="17057.384272"/>
   </TR>
   <TR>
    <TC Value="4"/>
    <TC Value="App4_BSM"/>
    <TC Value="4"/>
    <TC Value="8"/>
    <TC Value="187499"/>
    <TC Value="2989"/>
    <TC Value="3749980"/>
    <TC Value="59780"/>
    <TC Value="0.007971"/>
    <TC Value="28732192.392118"/>
    <TC Value="19294.346727"/>
   </TR>
   <TR>
    <TC Value="4"/>
    <TC Value="App4_BSM"/>
    <TC Value="4"/>
    <TC Value="9"/>
    <TC Value="187499"/>
    <TC Value="3162"/>
    <TC Value="3749980"/>
    <TC Value="63240"/>
    <TC Value="0.008432"/>
    <TC Value="28669485.905361"/>
    <TC Value="18238.694673"/>
   </TR>
   <TR>
    <TC Value="4"/>
    <TC Value="App4_BSM"/>
    <TC Value="4"/>
    <TC Value="10"/>
    <TC Value="187499"/>
    <TC Value="3203"/>
    <TC Value="3749980"/>
    <TC Value="64060"/>
    <TC Value="0.008541"/>
    <TC Value="28633029.145832"/>
    <TC Value="18005.220031"/>
   </TR>
   <TR>
    <TC Value="4"/>
    <TC Value="App4_BSM"/>
    <TC Value="4"/>
    <TC Value="11"/>
    <TC Value="187499"/>
    <TC Value="3600"/>
    <TC Value="3749980"/>
    <TC Value="72000"/>
    <TC Value="0.009600"/>
    <TC Value="36326632.630669"/>
    <TC Value="13023.599917"/>
   </TR>
   <TR>
    <TC Value="5 (Aggregated)"/>
    <TC Value="App5_BSM"/>
    <TC Value="5"/>
    <TC Value="0"/>
    <TC Value="187499"/>
    <TC Value="46131"/>
    <TC Value="3749980"/>
    <TC Value="922620"/>
    <TC Value="0.123016"/>
    <TC Value="29298963.517585"/>
    <TC Value="0.000000"/>
   </TR>
   <TR>
    <TC Value="5"/>
    <TC Value="App5_BSM"/>
    <TC Value="5"/>
    <TC Value="2"/>
    <TC Value="187499"/>
    <TC Value="5238"/>
    <TC Value="3749980"/>
    <TC Value="104760"/>
    <TC Value="0.013968"/>
    <TC Value="28872415.466581"/>
    <TC Value="11010.796586"/>
   </TR>
   <TR>
    <TC Value="5"/>
    <TC Value="App5_BSM"/>
    <TC Value="5"/>
    <TC Value="3"/>
    <TC Value="187499"/>
    <TC Value="5554"/>
    <TC Value="3749980"/>
    <TC Value="111080"/>
    <TC Value="0.014811"/>
    <TC Value="28838086.971806"/>
    <TC Value="10384.687495"/>
   </TR>
   <TR>
    <TC Value="5"/>
    <TC Value="App5_BSM"/>
    <TC Value="5"/>
    <TC Value="4"/>
    <TC Value="187499"/>
    <TC Value="6429"/>
    <TC Value="3749980"/>
    <TC Value="128580"/>
    <TC Value="0.017144"/>
    <TC Value="29005437.918877"/>
    <TC Value="8972.362470"/>
   </TR>
   <TR>
    <TC Value="5"/>
    <TC Value="App5_BSM"/>
    <TC Value="5"/>
    <TC Value="6"/>
    <TC Value="187499"/>
    <TC Value="6082"/>
    <TC Value="3749980"/>
    <TC Value="121640"/>
    <TC Value="0.016219"/>
    <TC Value="28884404.124349"/>
    <TC Value="9484.065716"/>
   </TR>
   <TR>
    <TC Value="5"/>
    <TC Value="App5_BSM"/>
    <TC Value="5"/>
    <TC Value="7"/>
    <TC Value="187499"/>
    <TC Value="4365"/>
    <TC Value="3749980"/>
    <TC Value="87300"/>
    <TC Value="0.011640"/>
    <TC Value="28089476.823782"/>
    <TC Value="13212.571627"/>
   </TR>
   <TR>
    <TC Value="5"/>
    <TC Value="App5_BSM"/>
    <TC Value="5"/>
    <TC Value="8"/>
    <TC Value="187499"/>
    <TC Value="3426"/>
    <TC Value="3749980"/>
    <TC Value="68520"/>
    <TC Value="0.009136"/>
    <TC Value="28458170.620047"/>
    <TC Value="16833.515860"/>
   </TR>
   <TR>
    <TC Value="5"/>
    <TC Value="App5_BSM"/>
    <TC Value="5"/>
    <TC Value="9"/>
    <TC Value="187499"/>
    <TC Value="3476"/>
    <TC Value="3749980"/>
    <TC Value="69520"/>
    <TC Value="0.009269"/>
    <TC Value="28882998.963556"/>
    <TC Value="16591.372230"/>
   </TR>
   <TR>
    <TC Value="5"/>
    <TC Value="App5_BSM"/>
    <TC Value="5"/>
    <TC Value="10"/>
    <TC Value="187499"/>
    <TC Value="3634"/>
    <TC Value="3749980"/>
    <TC Value="72680"/>
    <TC Value="0.009691"/>
    <TC Value="28818816.926896"/>
    <TC Value="15869.964977"/>
   </TR>
   <TR>
    <TC Value="5"/>
    <TC Value="App5_BSM"/>
    <TC Value="5"/>
    <TC Value="1"/>
    <TC Value="187499"/>
    <TC Value="3835"/>
    <TC Value="3749980"/>
    <TC Value="76700"/>
    <TC Value="0.010227"/>
    <TC Value="28948843.401432"/>
    <TC Value="15037.690483"/>
   </TR>
   <TR>
    <TC Value="5"/>
    <TC Value="App5_BSM"/>
    <TC Value="5"/>
    <TC Value="11"/>
    <TC Value="187499"/>
    <TC Value="4092"/>
    <TC Value="3749980"/>
    <TC Value="81840"/>
    <TC Value="0.010912"/>
    <TC Value="34649847.036992"/>
    <TC Value="11832.612828"/>
   </TR>
   <TR>
    <TC Value="6 (Aggregated)"/>
    <TC Value="App6_BSM"/>
    <TC Value="6"/>
    <TC Value="0"/>
    <TC Value="187499"/>
    <TC Value="49023"/>
    <TC Value="3749980"/>
    <TC Value="980460"/>
    <TC Value="0.130728"/>
    <TC Value="29178944.008948"/>
    <TC Value="0.000000"/>
   </TR>
   <TR>
    <TC Value="6"/>
    <TC Value="App6_BSM"/>
    <TC Value="6"/>
    <TC Value="1"/>
    <TC Value="187499"/>
    <TC Value="3618"/>
    <TC Value="3749980"/>
    <TC Value="72360"/>
    <TC Value="0.009648"/>
    <TC Value="29174123.046540"/>
    <TC Value="15938.122532"/>
   </TR>
   <TR>
    <TC Value="6"/>
    <TC Value="App6_BSM"/>
    <TC Value="6"/>
    <TC Value="2"/>
    <TC Value="187499"/>
    <TC Value="5269"/>
    <TC Value="3749980"/>
    <TC Value="105380"/>
    <TC Value="0.014051"/>
    <TC Value="28900857.540596"/>
    <TC Value="10945.016004"/>
   </TR>
   <TR>
    <TC Value="6"/>
    <TC Value="App6_BSM"/>
    <TC Value="6"/>
    <TC Value="3"/>
    <TC Value="187499"/>
    <TC Value="5269"/>
    <TC Value="3749980"/>
    <TC Value="105380"/>
    <TC Value="0.014051"/>
    <TC Value="28900601.088986"/>
    <TC Value="10945.013768"/>
   </TR>
   <TR>
    <TC Value="6"/>
    <TC Value="App6_BSM"/>
    <TC Value="6"/>
    <TC Value="4"/>
    <TC Value="187499"/>
    <TC Value="5854"/>
    <TC Value="3749980"/>
    <TC Value="117080"/>
    <TC Value="0.015611"/>
    <TC Value="28910787.159481"/>
    <TC Value="9851.898315"/>
   </TR>
   <TR>
    <TC Value="6"/>
    <TC Value="App6_BSM"/>
    <TC Value="6"/>
    <TC Value="5"/>
    <TC Value="187499"/>
    <TC Value="6583"/>
    <TC Value="3749980"/>
    <TC Value="131660"/>
    <TC Value="0.017555"/>
    <TC Value="28945265.988217"/>
    <TC Value="8761.823093"/>
   </TR>
   <TR>
    <TC Value="6"/>
    <TC Value="App6_BSM"/>
    <TC Value="6"/>
    <TC Value="7"/>
    <TC Value="187499"/>
    <TC Value="5669"/>
    <TC Value="3749980"/>
    <TC Value="113380"/>
    <TC Value="0.015117"/>
    <TC Value="28026998.528748"/>
    <TC Value="10173.531062"/>
   </TR>
   <TR>
    <TC Value="6"/>
    <TC Value="App6_BSM"/>
    <TC Value="6"/>
    <TC Value="8"/>
    <TC Value="187499"/>
    <TC Value="4369"/>
    <TC Value="3749980"/>
    <TC Value="87380"/>
    <TC Value="0.011651"/>
    <TC Value="28325803.471669"/>
    <TC Value="13199.125053"/>
   </TR>
   <TR>
    <TC Value="6"/>
    <TC Value="App6_BSM"/>
    <TC Value="6"/>
    <TC Value="9"/>
    <TC Value="187499"/>
    <TC Value="3861"/>
    <TC Value="3749980"/>
    <TC Value="77220"/>
    <TC Value="0.010296"/>
    <TC Value="28949173.443623"/>
    <TC Value="14935.427184"/>
   </TR>
   <TR>
    <TC Value="6"/>
    <TC Value="App6_BSM"/>
    <TC Value="6"/>
    <TC Value="10"/>
    <TC Value="187499"/>
    <TC Value="3892"/>
    <TC Value="3749980"/>
    <TC Value="77840"/>
    <TC Value="0.010379"/>
    <TC Value="28775621.003150"/>
    <TC Value="14816.473927"/>
   </TR>
   <TR>
    <TC Value="6"/>
    <TC Value="App6_BSM"/>
    <TC Value="6"/>
    <TC Value="11"/>
    <TC Value="187499"/>
    <TC Value="4639"/>
    <TC Value="3749980"/>
    <TC Value="92780"/>
    <TC Value="0.012371"/>
    <TC Value="33225503.293738"/>
    <TC Value="10850.680774"/>
   </TR>
   <TR>
    <TC Value="7 (Aggregated)"/>
    <TC Value="App7_BSM"/>
    <TC Value="7"/>
    <TC Value="0"/>
    <TC Value="187499"/>
    <TC Value="51667"/>
    <TC Value="3749980"/>
    <TC Value="1033340"/>
    <TC Value="0.137779"/>
    <TC Value="29208474.144764"/>
    <TC Value="0.000000"/>
   </TR>
   <TR>
    <TC Value="7"/>
    <TC Value="App7_BSM"/>
    <TC Value="7"/>
    <TC Value="1"/>
    <TC Value="187499"/>
    <TC Value="2999"/>
    <TC Value="3749980"/>
    <TC Value="59980"/>
    <TC Value="0.007997"/>
    <TC Value="28589260.373815"/>
    <TC Value="19234.701574"/>
   </TR>
   <TR>
    <TC Value="7"/>
    <TC Value="App7_BSM"/>
    <TC Value="7"/>
    <TC Value="2"/>
    <TC Value="187499"/>
    <TC Value="5358"/>
    <TC Value="3749980"/>
    <TC Value="107160"/>
    <TC Value="0.014288"/>
    <TC Value="29080224.298878"/>
    <TC Value="10766.922475"/>
   </TR>
   <TR>
    <TC Value="7"/>
    <TC Value="App7_BSM"/>
    <TC Value="7"/>
    <TC Value="3"/>
    <TC Value="187499"/>
    <TC Value="5351"/>
    <TC Value="3749980"/>
    <TC Value="107020"/>
    <TC Value="0.014269"/>
    <TC Value="29103753.670783"/>
    <TC Value="10780.998572"/>
   </TR>
   <TR>
    <TC Value="7"/>
    <TC Value="App7_BSM"/>
    <TC Value="7"/>
    <TC Value="4"/>
    <TC Value="187499"/>
    <TC Value="5488"/>
    <TC Value="3749980"/>
    <TC Value="109760"/>
    <TC Value="0.014635"/>
    <TC Value="29047380.250807"/>
    <TC Value="10512.002912"/>
   </TR>
   <TR>
    <TC Value="7"/>
    <TC Value="App7_BSM"/>
    <TC Value="7"/>
    <TC Value="5"/>
    <TC Value="187499"/>
    <TC Value="5883"/>
    <TC Value="3749980"/>
    <TC Value="117660"/>
    <TC Value="0.015688"/>
    <TC Value="28773289.989451"/>
    <TC Value="9806.632282"/>
   </TR>
   <TR>
    <TC Value="7"/>
    <TC Value="App7_BSM"/>
    <TC Value="7"/>
    <TC Value="6"/>
    <TC Value="187499"/>
    <TC Value="6463"/>
    <TC Value="3749980"/>
    <TC Value="129260"/>
    <TC Value="0.017235"/>
    <TC Value="28517154.739002"/>
    <TC Value="8927.197162"/>
   </TR>
   <TR>
    <TC Value="7"/>
    <TC Value="App7_BSM"/>
    <TC Value="7"/>
    <TC Value="8"/>
    <TC Value="187499"/>
    <TC Value="6001"/>
    <TC Value="3749980"/>
    <TC Value="120020"/>
    <TC Value="0.016003"/>
    <TC Value="28995988.325859"/>
    <TC Value="9613.658053"/>
   </TR>
   <TR>
    <TC Value="7"/>
    <TC Value="App7_BSM"/>
    <TC Value="7"/>
    <TC Value="9"/>
    <TC Value="187499"/>
    <TC Value="4514"/>
    <TC Value="3749980"/>
    <TC Value="90280"/>
    <TC Value="0.012037"/>
    <TC Value="28898476.004931"/>
    <TC Value="12778.821039"/>
   </TR>
   <TR>
    <TC Value="7"/>
    <TC Value="App7_BSM"/>
    <TC Value="7"/>
    <TC Value="10"/>
    <TC Value="187499"/>
    <TC Value="4514"/>
    <TC Value="3749980"/>
    <TC Value="90280"/>
    <TC Value="0.012037"/>
    <TC Value="28898476.004931"/>
    <TC Value="12778.821039"/>
   </TR>
   <TR>
    <TC Value="7"/>
    <TC Value="App7_BSM"/>
    <TC Value="7"/>
    <TC Value="11"/>
    <TC Value="187499"/>
    <TC Value="5096"/>
    <TC Value="3749980"/>
    <TC Value="101920"/>
    <TC Value="0.013589"/>
    <TC Value="32169738.593430"/>
    <TC Value="10187.033912"/>
   </TR>
   <TR>
    <TC Value="8 (Aggregated)"/>
    <TC Value="App8_BSM"/>
    <TC Value="8"/>
    <TC Value="0"/>
    <TC Value="187499"/>
    <TC Value="55625"/>
    <TC Value="3749980"/>
    <TC Value="1112500"/>
    <TC Value="0.148333"/>
    <TC Value="28890711.648821"/>
    <TC Value="0.000000"/>
   </TR>
   <TR>
    <TC Value="8"/>
    <TC Value="App8_BSM"/>
    <TC Value="8"/>
    <TC Value="1"/>
    <TC Value="187499"/>
    <TC Value="2719"/>
    <TC Value="3749980"/>
    <TC Value="54380"/>
    <TC Value="0.007251"/>
    <TC Value="28832347.489801"/>
    <TC Value="21207.201078"/>
   </TR>
   <TR>
    <TC Value="8"/>
    <TC Value="App8_BSM"/>
    <TC Value="8"/>
    <TC Value="2"/>
    <TC Value="187499"/>
    <TC Value="5705"/>
    <TC Value="3749980"/>
    <TC Value="114100"/>
    <TC Value="0.015213"/>
    <TC Value="28735871.496721"/>
    <TC Value="10108.328003"/>
   </TR>
   <TR>
    <TC Value="8"/>
    <TC Value="App8_BSM"/>
    <TC Value="8"/>
    <TC Value="3"/>
    <TC Value="187499"/>
    <TC Value="5702"/>
    <TC Value="3749980"/>
    <TC Value="114040"/>
    <TC Value="0.015205"/>
    <TC Value="28738899.840489"/>
    <TC Value="10113.647243"/>
   </TR>
   <TR>
    <TC Value="8"/>
    <TC Value="App8_BSM"/>
    <TC Value="8"/>
    <TC Value="4"/>
    <TC Value="187499"/>
    <TC Value="5695"/>
    <TC Value="3749980"/>
    <TC Value="113900"/>
    <TC Value="0.015187"/>
    <TC Value="28733562.827840"/>
    <TC Value="10126.067329"/>
   </TR>
   <TR>
    <TC Value="8"/>
    <TC Value="App8_BSM"/>
    <TC Value="8"/>
    <TC Value="5"/>
    <TC Value="187499"/>
    <TC Value="5878"/>
    <TC Value="3749980"/>
    <TC Value="117560"/>
    <TC Value="0.015675"/>
    <TC Value="28705202.394163"/>
    <TC Value="9811.047308"/>
   </TR>
   <TR>
    <TC Value="8"/>
    <TC Value="App8_BSM"/>
    <TC Value="8"/>
    <TC Value="6"/>
    <TC Value="187499"/>
    <TC Value="6198"/>
    <TC Value="3749980"/>
    <TC Value="123960"/>
    <TC Value="0.016528"/>
    <TC Value="28620824.998421"/>
    <TC Value="9304.846518"/>
   </TR>
   <TR>
    <TC Value="8"/>
    <TC Value="App8_BSM"/>
    <TC Value="8"/>
    <TC Value="7"/>
    <TC Value="187499"/>
    <TC Value="6766"/>
    <TC Value="3749980"/>
    <TC Value="135320"/>
    <TC Value="0.018043"/>
    <TC Value="28883934.709784"/>
    <TC Value="8524.443724"/>
   </TR>
   <TR>
    <TC Value="8"/>
    <TC Value="App8_BSM"/>
    <TC Value="8"/>
    <TC Value="9"/>
    <TC Value="187499"/>
    <TC Value="6057"/>
    <TC Value="3749980"/>
    <TC Value="121140"/>
    <TC Value="0.016152"/>
    <TC Value="28691326.469510"/>
    <TC Value="9521.653704"/>
   </TR>
   <TR>
    <TC Value="8"/>
    <TC Value="App8_BSM"/>
    <TC Value="8"/>
    <TC Value="10"/>
    <TC Value="187499"/>
    <TC Value="5175"/>
    <TC Value="3749980"/>
    <TC Value="103500"/>
    <TC Value="0.013800"/>
    <TC Value="28609818.431563"/>
    <TC Value="11143.303933"/>
   </TR>
   <TR>
    <TC Value="8"/>
    <TC Value="App8_BSM"/>
    <TC Value="8"/>
    <TC Value="11"/>
    <TC Value="187499"/>
    <TC Value="5730"/>
    <TC Value="3749980"/>
    <TC Value="114600"/>
    <TC Value="0.015280"/>
    <TC Value="30334512.825203"/>
    <TC Value="9458.720894"/>
   </TR>
   <TR>
    <TC Value="9 (Aggregated)"/>
    <TC Value="App9_BSM"/>
    <TC Value="9"/>
    <TC Value="0"/>
    <TC Value="187499"/>
    <TC Value="59270"/>
    <TC Value="3749980"/>
    <TC Value="1185400"/>
    <TC Value="0.158053"/>
    <TC Value="28771578.171985"/>
    <TC Value="0.000000"/>
   </TR>
   <TR>
    <TC Value="9"/>
    <TC Value="App9_BSM"/>
    <TC Value="9"/>
    <TC Value="2"/>
    <TC Value="187499"/>
    <TC Value="6199"/>
    <TC Value="3749980"/>
    <TC Value="123980"/>
    <TC Value="0.016531"/>
    <TC Value="28756604.856827"/>
    <TC Value="9309.229529"/>
   </TR>
   <TR>
    <TC Value="9"/>
    <TC Value="App9_BSM"/>
    <TC Value="9"/>
    <TC Value="3"/>
    <TC Value="187499"/>
    <TC Value="6199"/>
    <TC Value="3749980"/>
    <TC Value="123980"/>
    <TC Value="0.016531"/>
    <TC Value="28756604.856827"/>
    <TC Value="9309.229529"/>
   </TR>
   <TR>
    <TC Value="9"/>
    <TC Value="App9_BSM"/>
    <TC Value="9"/>
    <TC Value="4"/>
    <TC Value="187499"/>
    <TC Value="6196"/>
    <TC Value="3749980"/>
    <TC Value="123920"/>
    <TC Value="0.016523"/>
    <TC Value="28759616.921473"/>
    <TC Value="9313.725433"/>
   </TR>
   <TR>
    <TC Value="9"/>
    <TC Value="App9_BSM"/>
    <TC Value="9"/>
    <TC Value="5"/>
    <TC Value="187499"/>
    <TC Value="6220"/>
    <TC Value="3749980"/>
    <TC Value="124400"/>
    <TC Value="0.016587"/>
    <TC Value="28766292.417194"/>
    <TC Value="9277.800675"/>
   </TR>
   <TR>
    <TC Value="9"/>
    <TC Value="App9_BSM"/>
    <TC Value="9"/>
    <TC Value="6"/>
    <TC Value="187499"/>
    <TC Value="6321"/>
    <TC Value="3749980"/>
    <TC Value="126420"/>
    <TC Value="0.016856"/>
    <TC Value="28745316.106714"/>
    <TC Value="9129.669130"/>
   </TR>
   <TR>
    <TC Value="9"/>
    <TC Value="App9_BSM"/>
    <TC Value="9"/>
    <TC Value="7"/>
    <TC Value="187499"/>
    <TC Value="6536"/>
    <TC Value="3749980"/>
    <TC Value="130720"/>
    <TC Value="0.017429"/>
    <TC Value="28781265.329714"/>
    <TC Value="8829.558736"/>
   </TR>
   <TR>
    <TC Value="9"/>
    <TC Value="App9_BSM"/>
    <TC Value="9"/>
    <TC Value="8"/>
    <TC Value="187499"/>
    <TC Value="6799"/>
    <TC Value="3749980"/>
    <TC Value="135980"/>
    <TC Value="0.018131"/>
    <TC Value="28775863.359656"/>
    <TC Value="8488.310786"/>
   </TR>
   <TR>
    <TC Value="9"/>
    <TC Value="App9_BSM"/>
    <TC Value="9"/>
    <TC Value="10"/>
    <TC Value="187499"/>
    <TC Value="5982"/>
    <TC Value="3749980"/>
    <TC Value="119640"/>
    <TC Value="0.015952"/>
    <TC Value="28777654.914943"/>
    <TC Value="9646.811924"/>
   </TR>
   <TR>
    <TC Value="9"/>
    <TC Value="App9_BSM"/>
    <TC Value="9"/>
    <TC Value="1"/>
    <TC Value="187499"/>
    <TC Value="2400"/>
    <TC Value="3749980"/>
    <TC Value="48000"/>
    <TC Value="0.006400"/>
    <TC Value="28860860.800213"/>
    <TC Value="24040.911788"/>
   </TR>
   <TR>
    <TC Value="9"/>
    <TC Value="App9_BSM"/>
    <TC Value="9"/>
    <TC Value="11"/>
    <TC Value="187499"/>
    <TC Value="6418"/>
    <TC Value="3749980"/>
    <TC Value="128360"/>
    <TC Value="0.017115"/>
    <TC Value="28789582.432004"/>
    <TC Value="8931.892872"/>
   </TR>
   <TR>
    <TC Value="10 (Aggregated)"/>
    <TC Value="App10_BSM"/>
    <TC Value="10"/>
    <TC Value="0"/>
    <TC Value="187499"/>
    <TC Value="65770"/>
    <TC Value="3749980"/>
    <TC Value="1315400"/>
    <TC Value="0.175387"/>
    <TC Value="29025848.298371"/>
    <TC Value="0.000000"/>
   </TR>
   <TR>
    <TC Value="10"/>
    <TC Value="App10_BSM"/>
    <TC Value="10"/>
    <TC Value="2"/>
    <TC Value="187499"/>
    <TC Value="7066"/>
    <TC Value="3749980"/>
    <TC Value="141320"/>
    <TC Value="0.018843"/>
    <TC Value="29004476.689624"/>
    <TC Value="8162.227223"/>
   </TR>
   <TR>
    <TC Value="10"/>
    <TC Value="App10_BSM"/>
    <TC Value="10"/>
    <TC Value="3"/>
    <TC Value="187499"/>
    <TC Value="7066"/>
    <TC Value="3749980"/>
    <TC Value="141320"/>
    <TC Value="0.018843"/>
    <TC Value="29004476.689624"/>
    <TC Value="8162.227223"/>
   </TR>
   <TR>
    <TC Value="10"/>
    <TC Value="App10_BSM"/>
    <TC Value="10"/>
    <TC Value="4"/>
    <TC Value="187499"/>
    <TC Value="7066"/>
    <TC Value="3749980"/>
    <TC Value="141320"/>
    <TC Value="0.018843"/>
    <TC Value="29004476.689624"/>
    <TC Value="8162.227223"/>
   </TR>
   <TR>
    <TC Value="10"/>
    <TC Value="App10_BSM"/>
    <TC Value="10"/>
    <TC Value="5"/>
    <TC Value="187499"/>
    <TC Value="7066"/>
    <TC Value="3749980"/>
    <TC Value="141320"/>
    <TC Value="0.018843"/>
    <TC Value="29004476.689624"/>
    <TC Value="8162.227223"/>
   </TR>
   <TR>
    <TC Value="10"/>
    <TC Value="App10_BSM"/>
    <TC Value="10"/>
    <TC Value="6"/>
    <TC Value="187499"/>
    <TC Value="7066"/>
    <TC Value="3749980"/>
    <TC Value="141320"/>
    <TC Value="0.018843"/>
    <TC Value="29004476.689624"/>
    <TC Value="8162.227223"/>
   </TR>
   <TR>
    <TC Value="10"/>
    <TC Value="App10_BSM"/>
    <TC Value="10"/>
    <TC Value="7"/>
    <TC Value="187499"/>
    <TC Value="7066"/>
    <TC Value="3749980"/>
    <TC Value="141320"/>
    <TC Value="0.018843"/>
    <TC Value="29004476.689624"/>
    <TC Value="8162.227223"/>
   </TR>
   <TR>
    <TC Value="10"/>
    <TC Value="App10_BSM"/>
    <TC Value="10"/>
    <TC Value="8"/>
    <TC Value="187499"/>
    <TC Value="7066"/>
    <TC Value="3749980"/>
    <TC Value="141320"/>
    <TC Value="0.018843"/>
    <TC Value="29004476.689624"/>
    <TC Value="8162.227223"/>
   </TR>
   <TR>
    <TC Value="10"/>
    <TC Value="App10_BSM"/>
    <TC Value="10"/>
    <TC Value="9"/>
    <TC Value="187499"/>
    <TC Value="7066"/>
    <TC Value="3749980"/>
    <TC Value="141320"/>
    <TC Value="0.018843"/>
    <TC Value="29004476.689624"/>
    <TC Value="8162.227223"/>
   </TR>
   <TR>
    <TC Value="10"/>
    <TC Value="App10_BSM"/>
    <TC Value="10"/>
    <TC Value="1"/>
    <TC Value="187499"/>
    <TC Value="2229"/>
    <TC Value="3749980"/>
    <TC Value="44580"/>
    <TC Value="0.005944"/>
    <TC Value="28949019.379910"/>
    <TC Value="25865.450844"/>
   </TR>
   <TR>
    <TC Value="10"/>
    <TC Value="App10_BSM"/>
    <TC Value="10"/>
    <TC Value="11"/>
    <TC Value="187499"/>
    <TC Value="7013"/>
    <TC Value="3749980"/>
    <TC Value="140260"/>
    <TC Value="0.018701"/>
    <TC Value="29222532.450443"/>
    <TC Value="8169.367842"/>
   </TR>
  </TABLE>
 </MENU>
</NetSim_Metrics>
